game/__init__.py
game/game.py
mini_tic_tac_toe-0.0.2.dist-info/LICENCE
mini_tic_tac_toe-0.0.2.dist-info/METADATA
mini_tic_tac_toe-0.0.2.dist-info/WHEEL
mini_tic_tac_toe-0.0.2.dist-info/top_level.txt
mini_tic_tac_toe-0.0.2.dist-info/RECORD
